ez_setup.py
history.txt
setup.py
todo.txt
bin/magot
doc/model.jude
doc/model.png
doc/usecases.txt
src/py/Magot.egg-info/PKG-INFO
src/py/Magot.egg-info/SOURCES.txt
src/py/Magot.egg-info/entry_points.txt
src/py/Magot.egg-info/not-zip-safe
src/py/Magot.egg-info/requires.txt
src/py/Magot.egg-info/top_level.txt
src/py/magot/__init__.py
src/py/magot/accountHierarchy.py
src/py/magot/accountLedger.py
src/py/magot/commands.py
src/py/magot/dimension.py
src/py/magot/gui.py
src/py/magot/guiutil.py
src/py/magot/magot.ini
src/py/magot/model.py
src/py/magot/refdata.py
src/py/magot/storage.py
src/py/magot/util.py
src/py/magot/sandbox/__init__.py
src/py/magot/sandbox/test.py
src/py/magot/tests/__init__.py
src/py/magot/tests/test_components.py
src/py/magot/tests/test_fmtparse.py
src/py/magot/tests/test_model.py
src/py/magot/tests/test_multi_dimensions.py
src/py/magot/tests/test_real_estate.py
src/py/magot/tests/test_refdata.py
src/py/magot/tests/test_storage.py
web/AccountHierarchy.png
web/AccountLedger.png
web/GroupedByDimension.png
web/GroupedByDimension2.png
web/apartmentAnalysis.txt
web/chinese.jpg
web/index.html
