Metadata-Version: 1.0
Name: Magot
Version: 0.2.0
Summary: A cross-platform personal finance manager.
Home-page: http://developer.berlios.de/projects/magot/
Author: Jean-Philippe Dutreve
Author-email: jdutreve@users.berlios.de
License: LGPL
Download-URL: http://download.berlios.de/magot/
Keywords: accounting,finance,Python,WxPython,PEAK,component,framework,agile,OLAP
Platform: UNIX
Platform: Windows
Classifier: Development Status :: 4 - Beta
Classifier: Intended Audience :: Developers
Classifier: License :: OSI Approved :: GNU Library or Lesser General Public License (LGPL)
Classifier: Operating System :: OS Independent
Classifier: Programming Language :: Python
Classifier: Topic :: Office/Business :: Financial :: Accounting
